blessedtable.py
blessedtable-1.0.0.dist-info/LICENSE
blessedtable-1.0.0.dist-info/METADATA
blessedtable-1.0.0.dist-info/WHEEL
blessedtable-1.0.0.dist-info/top_level.txt
blessedtable-1.0.0.dist-info/RECORD
