Metadata-Version: 2.1
Name: blessedtable
Version: 1.0.0
Summary: module for creating simple colorful formatted ASCII tables
Home-page: https://github.com/paul-shuvo/blessedtable
Author: Shuvo Kumar Paul
Author-email: shuvo.k.paul@gmail.com
License: MIT
Download-URL: https://github.com/paul-shuvo/blessedtable/archive/refs/tags/v1.0.0.zip
Keywords: terminal,sequences,tty,curses,ncurses,formatting,style,color,console,keyboard,ansi,xterm,table,ascii
Platform: any
Classifier: Environment :: Console
Classifier: Intended Audience :: Developers
Classifier: Intended Audience :: End Users/Desktop
Classifier: License :: OSI Approved :: MIT License
Classifier: Operating System :: Microsoft :: Windows
Classifier: Operating System :: POSIX
Classifier: Operating System :: MacOS
Classifier: Topic :: Software Development :: Libraries :: Python Modules
Classifier: Topic :: Text Processing
Classifier: Topic :: Utilities
Classifier: Programming Language :: Python
Classifier: Programming Language :: Python :: 2
Classifier: Programming Language :: Python :: 2.7
Classifier: Programming Language :: Python :: 3
Classifier: Programming Language :: Python :: 3.5
Classifier: Programming Language :: Python :: 3.6
Classifier: Programming Language :: Python :: 3.7
Classifier: Programming Language :: Python :: 3.8
Classifier: Programming Language :: Python :: 3.9
License-File: LICENSE
Requires-Dist: blessed
Requires-Dist: texttable (==1.6.4)
